sverification/__init__.py
sverification/compare_metadata.py
sverification/font_data_extractor.py
sverification/pdf_name_extractor.py
sverification/statements_font_data.json
sverification/statements_metadata.json
sverification-0.1.2.dist-info/licenses/LICENSE
tests/__init__.py
tests/conftest.py
tests/test_compare_metadata.py
tests/test_font_comparison.py
tests/test_integration.py
tests/test_pdf_name_extractor.py
tests/test_verbose_verification.py
sverification-0.1.2.dist-info/METADATA
sverification-0.1.2.dist-info/WHEEL
sverification-0.1.2.dist-info/entry_points.txt
sverification-0.1.2.dist-info/top_level.txt
sverification-0.1.2.dist-info/RECORD
