Metadata-Version: 2.4
Name: sverification
Version: 0.1.2
Summary: A tool for verifying PDF statements from Tanzanian and beyond institutions
Home-page: https://github.com/Tausi-Africa/statement-verification
Author: Alex Mkwizu @ Black Swan AI
Author-email: alex@bsa.ai
Project-URL: Bug Tracker, https://github.com/Tausi-Africa/statement-verification/issues
Project-URL: Repository, https://github.com/Tausi-Africa/statement-verification
Keywords: pdf verification statements metadata financial
Classifier: Development Status :: 4 - Beta
Classifier: Intended Audience :: Developers
Classifier: Intended Audience :: Financial and Insurance Industry
Classifier: Programming Language :: Python :: 3
Classifier: Programming Language :: Python :: 3.8
Classifier: Programming Language :: Python :: 3.9
Classifier: Programming Language :: Python :: 3.10
Classifier: Programming Language :: Python :: 3.11
Classifier: Programming Language :: Python :: 3.12
Classifier: License :: Other/Proprietary License
Classifier: Operating System :: MacOS
Classifier: Operating System :: POSIX :: Linux
Classifier: Topic :: Office/Business :: Financial
Classifier: Topic :: Software Development :: Libraries :: Python Modules
Requires-Python: >=3.8
License-File: LICENSE
Requires-Dist: pdforensic-authentic-check>=0.1.41
Requires-Dist: pdfplumber>=0.6.0
Requires-Dist: pdf-font-checker>=0.1.1
Provides-Extra: test
Requires-Dist: pytest>=7.0.0; extra == "test"
Requires-Dist: pytest-cov>=4.0.0; extra == "test"
Provides-Extra: dev
Requires-Dist: pytest>=7.0.0; extra == "dev"
Requires-Dist: pytest-cov>=4.0.0; extra == "dev"
Requires-Dist: black; extra == "dev"
Requires-Dist: flake8; extra == "dev"
Dynamic: author
Dynamic: author-email
Dynamic: classifier
Dynamic: description
Dynamic: description-content-type
Dynamic: home-page
Dynamic: keywords
Dynamic: license-file
Dynamic: project-url
Dynamic: provides-extra
Dynamic: requires-dist
Dynamic: requires-python
Dynamic: summary
